mcdm_scheduler/__init__.py
mcdm_scheduler/algorithm/__init__.py
mcdm_scheduler/algorithm/src.py
mcdm_scheduler/util/__init__.py
mcdm_scheduler/util/fuzzy_ppf_ahp.py
mcdm_scheduler/util/ga.py
mcdm_scheduler/util/ht2fs.py
mcdm_scheduler-1.5.9.dist-info/LICENSE
mcdm_scheduler-1.5.9.dist-info/METADATA
mcdm_scheduler-1.5.9.dist-info/WHEEL
mcdm_scheduler-1.5.9.dist-info/top_level.txt
mcdm_scheduler-1.5.9.dist-info/RECORD
