Metadata-Version: 2.1
Name: mcdm-scheduler
Version: 1.5.9
Summary: A Library Incorporating a MCDM tools for Scheduling Problems
Home-page: https://github.com/Valdecy/mcdm_scheduler
Author: Valdecy Pereira
Author-email: valdecy.pereira@gmail.com
License: GNU
License-File: LICENSE
Requires-Dist: matplotlib
Requires-Dist: numpy
